[{"id": "74039377", "title": "あっぴぃの おみあしチラリタイム…♡", "illustType": 0, "xRestrict": 0, "restrict": 0, "sl": 4, "url": "https://i.pximg.net/c/250x250_80_a2/img-master/img/2019/04/04/18/15/24/74039377_p0_square1200.jpg", "description": "", "tags": ["MikuMikuDance", "MMD", "あぴミク", "ままま式あぴミク", "初音ミク", "足指", "足フェチ", "生足", "ふともも", "素足"], "userId": "16221870", "userName": "海冥", "width": 1500, "height": 1000, "pageCount": 1, "isBookmarkable": true, "bookmarkData": null, "alt": "#MikuMikuDance あっぴぃの おみあしチラリタイム…♡ - 海冥的插画", "titleCaptionTranslation": {"workTitle": null, "workCaption": null}, "createDate": "2019-04-04T18:15:24+09:00", "updateDate": "2019-04-04T18:15:24+09:00", "isUnlisted": false, "isMasked": false, "profileImageUrl": "https://i.pximg.net/user-profile/img/2016/06/27/16/15/45/11121668_a0995c94673a7eee42fa04aa694f85f7_50.png"}, {"id": "73629573", "title": "【あっぴぃ萌えリンク】おみあし見せつけるの…っ♡", "illustType": 0, "xRestrict": 0, "restrict": 0, "sl": 4, "url": "https://i.pximg.net/c/250x250_80_a2/img-master/img/2019/03/11/18/56/03/73629573_p0_square1200.jpg", "description": "", "tags": ["あっぴぃ萌えリンク", "MikuMikuDance", "MMD", "初音ミク", "あぴミク", "ままま式あぴミク", "ふともも", "足フェチ", "制服素足", "生足"], "userId": "16221870", "userName": "海冥", "width": 2000, "height": 1500, "pageCount": 1, "isBookmarkable": true, "bookmarkData": null, "alt": "#あっぴぃ萌えリンク 【あっぴぃ萌えリンク】おみあし見せつけるの…っ♡ - 海冥的插画", "titleCaptionTranslation": {"workTitle": null, "workCaption": null}, "createDate": "2019-03-11T18:56:03+09:00", "updateDate": "2019-03-11T18:56:03+09:00", "isUnlisted": false, "isMasked": false, "profileImageUrl": "https://i.pximg.net/user-profile/img/2016/06/27/16/15/45/11121668_a0995c94673a7eee42fa04aa694f85f7_50.png"}, {"id": "83831541", "title": "123", "illustType": 0, "xRestrict": 0, "restrict": 0, "sl": 2, "url": "https://i.pximg.net/c/250x250_80_a2/img-master/img/2020/08/21/15/47/05/83831541_p0_square1200.jpg", "description": "", "tags": ["初音ミク生誕祭2020", "VOCALOID", "初音ミク"], "userId": "17316747", "userName": "しずだま", "width": 2000, "height": 1500, "pageCount": 1, "isBookmarkable": true, "bookmarkData": null, "alt": "#初音ミク生誕祭2020 123 - しずだま的插画", "titleCaptionTranslation": {"workTitle": null, "workCaption": null}, "createDate": "2020-08-21T15:47:05+09:00", "updateDate": "2020-08-21T15:47:05+09:00", "isUnlisted": false, "isMasked": false, "profileImageUrl": "https://i.pximg.net/user-profile/img/2021/01/11/01/06/30/19982170_ad6e8a37fcebc37a9a4381a2893a074d_50.jpg"}, {"id": "3185221", "title": "ミク「KAITO先輩、リコーダー持ってませんか？」", "illustType": 0, "xRestrict": 0, "restrict": 0, "sl": 2, "url": "https://i.pximg.net/c/250x250_80_a2/img-master/img/2009/02/21/20/58/05/3185221_p0_square1200.jpg", "description": "", "tags": ["ミクカイ", "初音ミク", "相方に激しく同意", "KAITO", "VOCALOID", "こいつぁひどくかわいい", "漫画"], "userId": "60803", "userName": "ゆうひ", "width": 276, "height": 800, "pageCount": 1, "isBookmarkable": true, "bookmarkData": null, "alt": "#ミクカイ ミク「KAITO先輩、リコーダー持ってませんか？」 - ゆうひ的插画", "titleCaptionTranslation": {"workTitle": null, "workCaption": null}, "createDate": "2009-02-21T20:58:05+09:00", "updateDate": "2009-02-21T20:58:05+09:00", "isUnlisted": false, "isMasked": false, "profileImageUrl": "https://i.pximg.net/user-profile/img/2012/08/29/04/07/19/5077603_3dbcd8bb20bd2e224bb75b652aa9da3b_50.gif"}, {"id": "58979365", "title": "中秋MIKU", "illustType": 0, "xRestrict": 0, "restrict": 0, "sl": 4, "url": "https://i.pximg.net/c/250x250_80_a2/img-master/img/2016/09/14/19/58/48/58979365_p0_square1200.jpg", "description": "", "tags": ["VOCALOID", "初音ミク", "中秋明月ミク", "MIKU", "魅惑のふともも", "チャイナドレス", "孔明灯"], "userId": "11127575", "userName": "DONICA", "width": 2480, "height": 3507, "pageCount": 1, "isBookmarkable": true, "bookmarkData": null, "alt": "#VOCALOID 中秋MIKU - DONICA的插画", "titleCaptionTranslation": {"workTitle": null, "workCaption": null}, "createDate": "2016-09-14T19:58:48+09:00", "updateDate": "2016-09-14T19:58:48+09:00", "isUnlisted": false, "isMasked": false, "profileImageUrl": "https://i.pximg.net/user-profile/img/2021/08/28/16/35/14/21312405_e49426d3d6226837d6d81c5209d3a8aa_50.jpg"}, {"id": "1037193", "title": "テールコンビ", "illustType": 0, "xRestrict": 0, "restrict": 0, "sl": 2, "url": "https://i.pximg.net/c/250x250_80_a2/img-master/img/2008/06/24/20/43/54/1037193_p0_square1200.jpg", "description": "", "tags": ["がくっぽいど", "キューティクル", "世界が嫉妬する髪", "以前髪を食ってたような…", "初音ミク", "神威がくぽ", "ティモテティモテティモテ～", "みくぽ", "がくミク"], "userId": "86498", "userName": "n太", "width": 600, "height": 500, "pageCount": 1, "isBookmarkable": true, "bookmarkData": null, "alt": "#がくっぽいど テールコンビ - n太的插画", "titleCaptionTranslation": {"workTitle": null, "workCaption": null}, "createDate": "2008-06-24T20:43:54+09:00", "updateDate": "2008-06-24T20:43:54+09:00", "isUnlisted": false, "isMasked": false, "profileImageUrl": "https://i.pximg.net/user-profile/img/2016/06/02/21/37/14/11011326_c4ec21fc6e14bea0d1151ab026aede89_50.jpg"}, {"id": "45691085", "title": "ミク誕おめです！", "illustType": 1, "xRestrict": 0, "restrict": 0, "sl": 2, "url": "https://i.pximg.net/c/250x250_80_a2/img-master/img/2014/08/31/00/34/24/45691085_p0_square1200.jpg", "description": "", "tags": ["漫画", "鏡音レン", "初音ミク", "レンミク", "ミク誕生祭2014", "VOCALOID50users入り"], "userId": "2547828", "userName": "ナ☆ギ", "width": 768, "height": 1024, "pageCount": 13, "isBookmarkable": true, "bookmarkData": null, "alt": "#鏡音レン ミク誕おめです！ - ナ☆ギ的漫画", "titleCaptionTranslation": {"workTitle": null, "workCaption": null}, "createDate": "2014-08-31T00:34:24+09:00", "updateDate": "2014-08-31T00:34:24+09:00", "isUnlisted": false, "isMasked": false, "profileImageUrl": "https://i.pximg.net/user-profile/img/2013/06/29/19/13/17/6439483_e206ff0c39e4be036a3619ddb2ba297a_50.png"}, {"id": "64722989", "title": "初音ミク 10TH 生日快乐", "illustType": 0, "xRestrict": 0, "restrict": 0, "sl": 2, "url": "https://i.pximg.net/c/250x250_80_a2/img-master/img/2017/08/31/23/56/06/64722989_p0_square1200.jpg", "description": "", "tags": ["初音ミク10thイラコン", "VOCALOID", "初音ミク", "初音ミク生誕祭2017"], "userId": "1683477", "userName": "冰冫冰", "width": 827, "height": 1169, "pageCount": 1, "isBookmarkable": true, "bookmarkData": null, "alt": "#初音ミク10thイラコン 初音ミク 10TH 生日快乐 - 冰冫冰的插画", "titleCaptionTranslation": {"workTitle": null, "workCaption": null}, "createDate": "2017-08-31T23:56:06+09:00", "updateDate": "2017-08-31T23:56:06+09:00", "isUnlisted": false, "isMasked": false, "profileImageUrl": "https://i.pximg.net/user-profile/img/2012/03/26/17/34/39/4394537_de9fa6bf2ee2df92675fe90279cba379_50.jpg"}, {"id": "46504953", "title": "その断頭台を見上げたら", "illustType": 0, "xRestrict": 0, "restrict": 0, "sl": 2, "url": "https://i.pximg.net/c/250x250_80_a2/img-master/img/2014/10/12/12/11/10/46504953_p0_square1200.jpg", "description": "", "tags": ["VOCALOID", "二次創作", "初音ミク", "千本桜", "らくがき", "壱ノ桜・桜花", "ProjectDIVA"], "userId": "541041", "userName": "杉野こむら", "width": 1640, "height": 1000, "pageCount": 1, "isBookmarkable": true, "bookmarkData": null, "alt": "#VOCALOID その断頭台を見上げたら - 杉野こむら的插画", "titleCaptionTranslation": {"workTitle": null, "workCaption": null}, "createDate": "2014-10-12T12:11:10+09:00", "updateDate": "2014-10-12T12:11:10+09:00", "isUnlisted": false, "isMasked": false, "profileImageUrl": "https://i.pximg.net/user-profile/img/2014/03/09/21/09/44/7577815_ffd4a4c8ac1d7e9925da80f6b28872b0_50.jpg"}, {"id": "72109905", "title": "初音 龙神2020", "illustType": 0, "xRestrict": 0, "restrict": 0, "sl": 2, "url": "https://i.pximg.net/c/250x250_80_a2/img-master/img/2018/12/14/19/46/53/72109905_p0_square1200.jpg", "description": "", "tags": ["女の子", "少女", "制服", "初音ミク", "VOCALOID", "miku", "セブンスドラゴン", "セブンスドラゴン2020"], "userId": "23381353", "userName": "Aiee丨虾仁饭", "width": 3000, "height": 1900, "pageCount": 4, "isBookmarkable": true, "bookmarkData": null, "alt": "#女の子 初音 龙神2020 - Aiee丨虾仁饭的插画", "titleCaptionTranslation": {"workTitle": null, "workCaption": null}, "createDate": "2018-12-14T19:46:53+09:00", "updateDate": "2018-12-14T19:46:53+09:00", "isUnlisted": false, "isMasked": false, "profileImageUrl": "https://i.pximg.net/user-profile/img/2017/12/27/12/59/55/13609575_c6b5e58a69c5a4b04b818f5f63c4a400_50.png"}, {"id": "68514073", "title": "练习", "illustType": 0, "xRestrict": 0, "restrict": 0, "sl": 2, "url": "https://i.pximg.net/c/250x250_80_a2/img-master/img/2018/05/01/21/08/53/68514073_p0_square1200.jpg", "description": "", "tags": ["miku", "初音ミク"], "userId": "4995521", "userName": "Minccc", "width": 2480, "height": 3508, "pageCount": 1, "isBookmarkable": true, "bookmarkData": null, "alt": "#miku 练习 - Minccc的插画", "titleCaptionTranslation": {"workTitle": null, "workCaption": null}, "createDate": "2018-05-01T21:08:53+09:00", "updateDate": "2018-05-01T21:08:53+09:00", "isUnlisted": false, "isMasked": false, "profileImageUrl": "https://i.pximg.net/user-profile/img/2020/05/20/02/32/22/18658388_79989650d8a462fd26d30f6308bdd0b5_50.png"}, {"id": "11470601", "title": "サンドリヨンでコラボ", "illustType": 0, "xRestrict": 0, "restrict": 0, "sl": 2, "url": "https://i.pximg.net/c/250x250_80_a2/img-master/img/2010/06/24/01/56/38/11470601_p0_square1200.jpg", "description": "", "tags": ["VOCALOID", "KAITO", "初音ミク", "サンドリヨン", "カイミク"], "userId": "385912", "userName": "カナデ", "width": 1024, "height": 768, "pageCount": 1, "isBookmarkable": true, "bookmarkData": null, "alt": "#VOCALOID サンドリヨンでコラボ - カナデ的插画", "titleCaptionTranslation": {"workTitle": null, "workCaption": null}, "createDate": "2010-06-24T01:56:38+09:00", "updateDate": "2010-06-24T01:56:38+09:00", "isUnlisted": false, "isMasked": false, "profileImageUrl": "https://i.pximg.net/user-profile/img/2015/06/01/02/32/21/9436007_3e4f8ed4c8638b7d07a17d44efaf87e4_50.jpg"}, {"id": "64140677", "title": "砂の惑星", "illustType": 0, "xRestrict": 0, "restrict": 0, "sl": 2, "url": "https://i.pximg.net/c/250x250_80_a2/img-master/img/2017/07/31/02/12/03/64140677_p0_square1200.jpg", "description": "", "tags": ["VOCALOID", "砂の惑星", "初音ミク"], "userId": "15042792", "userName": "おちゃこ", "width": 1280, "height": 1024, "pageCount": 1, "isBookmarkable": true, "bookmarkData": null, "alt": "#VOCALOID 砂の惑星 - おちゃこ的插画", "titleCaptionTranslation": {"workTitle": null, "workCaption": null}, "createDate": "2017-07-31T02:12:03+09:00", "updateDate": "2017-07-31T02:12:03+09:00", "isUnlisted": false, "isMasked": false, "profileImageUrl": "https://i.pximg.net/user-profile/img/2017/11/15/01/30/50/13457830_7d53ab6d846dcae076c38e6692c0160c_50.jpg"}, {"id": "68247965", "title": "君の声が好き", "illustType": 0, "xRestrict": 0, "restrict": 0, "sl": 2, "url": "https://i.pximg.net/c/250x250_80_a2/img-master/img/2018/04/15/21/07/47/68247965_p0_square1200.jpg", "description": "", "tags": ["初音ミク"], "userId": "10622626", "userName": "柑橘系の缶詰", "width": 4093, "height": 2894, "pageCount": 1, "isBookmarkable": true, "bookmarkData": null, "alt": "#初音ミク 君の声が好き - 柑橘系の缶詰的插画", "titleCaptionTranslation": {"workTitle": null, "workCaption": null}, "createDate": "2018-04-15T21:07:47+09:00", "updateDate": "2018-04-15T21:07:47+09:00", "isUnlisted": false, "isMasked": false, "profileImageUrl": "https://i.pximg.net/user-profile/img/2018/09/06/14/27/21/14742486_b0958b39fa04d2d1bd04da2e702041ad_50.png"}, {"id": "65142849", "title": "ボブミクちゃん", "illustType": 0, "xRestrict": 0, "restrict": 0, "sl": 2, "url": "https://i.pximg.net/c/250x250_80_a2/img-master/img/2017/09/26/12/32/13/65142849_p0_square1200.jpg", "description": "", "tags": ["初音ミク", "ボブミク"], "userId": "8173993", "userName": "禊(ＲｉＡ)", "width": 768, "height": 1024, "pageCount": 1, "isBookmarkable": true, "bookmarkData": null, "alt": "#初音ミク ボブミクちゃん - 禊(ＲｉＡ)的插画", "titleCaptionTranslation": {"workTitle": null, "workCaption": null}, "createDate": "2017-09-26T12:32:13+09:00", "updateDate": "2017-09-26T12:32:13+09:00", "isUnlisted": false, "isMasked": false, "profileImageUrl": "https://i.pximg.net/user-profile/img/2020/06/16/23/16/17/18837024_38d47d8363ba1c89184d601a4316545f_50.png"}, {"id": "77659177", "title": "お誕生日おめでとう。", "illustType": 0, "xRestrict": 0, "restrict": 0, "sl": 2, "url": "https://i.pximg.net/c/250x250_80_a2/img-master/img/2019/11/05/00/19/04/77659177_p0_square1200.jpg", "description": "", "tags": ["VOCALOID", "MEIKO生誕祭2019", "MEIKO", "初音ミクシンフォニー", "VOCALOID50users入り"], "userId": "3085372", "userName": "チャレ", "width": 1181, "height": 1748, "pageCount": 1, "isBookmarkable": true, "bookmarkData": null, "alt": "#VOCALOID お誕生日おめでとう。 - チャレ的插画", "titleCaptionTranslation": {"workTitle": null, "workCaption": null}, "createDate": "2019-11-05T00:19:04+09:00", "updateDate": "2019-11-05T00:19:04+09:00", "isUnlisted": false, "isMasked": false, "profileImageUrl": "https://i.pximg.net/user-profile/img/2012/04/22/11/33/45/4510526_8e21fa0768d068bac8765c497a1a2fe9_50.jpg"}, {"id": "79041145", "title": "仲良くゲーム", "illustType": 0, "xRestrict": 0, "restrict": 0, "sl": 2, "url": "https://i.pximg.net/c/250x250_80_a2/img-master/img/2020/01/22/22/10/28/79041145_p0_square1200.jpg", "description": "", "tags": ["初音ミク", "VOCALOID", "Hello,Goodnight.", "ハツネミク"], "userId": "21164353", "userName": "コロコロ", "width": 2048, "height": 1536, "pageCount": 1, "isBookmarkable": true, "bookmarkData": null, "alt": "#初音ミク 仲良くゲーム - コロコロ的插画", "titleCaptionTranslation": {"workTitle": null, "workCaption": null}, "createDate": "2020-01-22T22:10:28+09:00", "updateDate": "2020-01-22T22:10:28+09:00", "isUnlisted": false, "isMasked": false, "profileImageUrl": "https://i.pximg.net/user-profile/img/2021/02/15/21/11/53/20196792_a93c1c8e40b844607b2452ae3e40ddde_50.png"}, {"id": "85476793", "title": "みくさん", "illustType": 0, "xRestrict": 0, "restrict": 0, "sl": 2, "url": "https://i.pximg.net/c/250x250_80_a2/img-master/img/2020/11/05/17/31/36/85476793_p0_square1200.jpg", "description": "", "tags": ["初音ミク"], "userId": "8635206", "userName": "のりもとパイン", "width": 2057, "height": 2072, "pageCount": 1, "isBookmarkable": true, "bookmarkData": null, "alt": "#初音ミク みくさん - のりもとパイン的插画", "titleCaptionTranslation": {"workTitle": null, "workCaption": null}, "createDate": "2020-11-05T17:31:36+09:00", "updateDate": "2020-11-05T17:31:36+09:00", "isUnlisted": false, "isMasked": false, "profileImageUrl": "https://i.pximg.net/user-profile/img/2021/09/12/19/44/00/21401112_b2663955cb4e40fd4959ce875a8c3b9f_50.png"}, {"id": "82152973", "title": "落書き", "illustType": 0, "xRestrict": 0, "restrict": 0, "sl": 2, "url": "https://i.pximg.net/c/250x250_80_a2/img-master/img/2020/06/07/13/39/02/82152973_p0_square1200.jpg", "description": "", "tags": ["初音ミク", "VOCALOID", "コロミク"], "userId": "21164353", "userName": "コロコロ", "width": 2048, "height": 1536, "pageCount": 1, "isBookmarkable": true, "bookmarkData": null, "alt": "#初音ミク 落書き - コロコロ的插画", "titleCaptionTranslation": {"workTitle": null, "workCaption": null}, "createDate": "2020-06-07T13:39:02+09:00", "updateDate": "2020-06-07T13:39:02+09:00", "isUnlisted": false, "isMasked": false, "profileImageUrl": "https://i.pximg.net/user-profile/img/2021/02/15/21/11/53/20196792_a93c1c8e40b844607b2452ae3e40ddde_50.png"}, {"id": "30656665", "title": "みみ", "illustType": 0, "xRestrict": 0, "restrict": 0, "sl": 2, "url": "https://i.pximg.net/c/250x250_80_a2/img-master/img/2012/10/08/00/18/59/30656665_p0_square1200.jpg", "description": "", "tags": ["VOCALOID", "初音ミク"], "userId": "1213038", "userName": "hado", "width": 384, "height": 560, "pageCount": 1, "isBookmarkable": true, "bookmarkData": null, "alt": "#VOCALOID みみ - hado的插画", "titleCaptionTranslation": {"workTitle": null, "workCaption": null}, "createDate": "2012-10-08T00:18:59+09:00", "updateDate": "2012-10-08T00:18:59+09:00", "isUnlisted": false, "isMasked": false, "profileImageUrl": "https://i.pximg.net/user-profile/img/2017/12/28/06/29/26/13612909_40b13d11a1a6adc1bcd610fc18ee10a4_50.png"}, {"id": "72299141", "title": "メリー・クリスマス", "illustType": 0, "xRestrict": 0, "restrict": 0, "sl": 2, "url": "https://i.pximg.net/c/250x250_80_a2/img-master/img/2018/12/25/23/25/50/72299141_p0_square1200.jpg", "description": "", "tags": ["VOCALOID", "ボーカロイド", "初音ミク", "メリー・クリスマス", "Xmas2018", "クリスマス"], "userId": "1088995", "userName": "R.P.S.", "width": 1440, "height": 2160, "pageCount": 1, "isBookmarkable": true, "bookmarkData": null, "alt": "#VOCALOID メリー・クリスマス - R.P.S.的插画", "titleCaptionTranslation": {"workTitle": null, "workCaption": null}, "createDate": "2018-12-25T23:25:50+09:00", "updateDate": "2018-12-25T23:25:50+09:00", "isUnlisted": false, "isMasked": false, "profileImageUrl": "https://i.pximg.net/user-profile/img/2021/09/04/10/32/30/21352569_c4e4e29af608848dd39b4f2a4d6006bb_50.jpg"}, {"id": "74564577", "title": "練習中：假日福利56(貧乳版)", "illustType": 2, "xRestrict": 1, "restrict": 0, "sl": 6, "url": "https://i.pximg.net/c/250x250_80_a2/img-master/img/2019/05/05/01/38/12/74564577_square1200.jpg", "description": "", "tags": ["R-18", "動圖", "初音ミク", "MMD", "MikuMikuDance", "VOCALOID", "うごイラ"], "userId": "8482094", "userName": "呆音", "width": 720, "height": 405, "pageCount": 1, "isBookmarkable": true, "bookmarkData": null, "alt": "#動圖 練習中：假日福利56(貧乳版) - 呆音的动图", "titleCaptionTranslation": {"workTitle": null, "workCaption": null}, "createDate": "2019-05-05T01:38:12+09:00", "updateDate": "2019-05-05T01:38:12+09:00", "isUnlisted": false, "isMasked": false, "profileImageUrl": "https://i.pximg.net/user-profile/img/2020/11/09/03/04/35/19640268_0d2b33106917263f0d993aa56c637793_50.png"}, {"id": "37729281", "title": "初音ミクさんのえっちな画像がほしかったから自分で作ってみた", "illustType": 1, "xRestrict": 1, "restrict": 0, "sl": 6, "url": "https://i.pximg.net/c/250x250_80_a2/img-master/img/2013/08/11/20/48/42/37729281_p0_square1200.jpg", "description": "", "tags": ["R-18", "3Dカスタム少女", "vocaloid", "ボーカロイド", "初音ミク", "スクール水着", "透け", "お漏らし", "アヘ顔ダブルピース"], "userId": "844737", "userName": "δケイδ＠ウシ君", "width": 656, "height": 799, "pageCount": 3, "isBookmarkable": true, "bookmarkData": null, "alt": "#3Dカスタム少女 初音ミクさんのえっちな画像がほしかったから自分で作ってみた - δケイδ＠ウシ君的漫画", "titleCaptionTranslation": {"workTitle": null, "workCaption": null}, "createDate": "2013-08-11T20:48:42+09:00", "updateDate": "2013-08-11T20:48:42+09:00", "isUnlisted": false, "isMasked": false, "profileImageUrl": "https://i.pximg.net/user-profile/img/2013/01/03/18/45/42/5633707_8842097f2228586938e936b1c1e16cf1_50.png"}, {"id": "66225429", "title": "トラブル２連発", "illustType": 0, "xRestrict": 0, "restrict": 0, "sl": 2, "url": "https://i.pximg.net/c/250x250_80_a2/img-master/img/2017/12/09/22/19/22/66225429_p0_square1200.jpg", "description": "", "tags": ["初音ミク", "VOCALOID", "ボカロ"], "userId": "17764467", "userName": "ねこみん", "width": 800, "height": 1052, "pageCount": 2, "isBookmarkable": true, "bookmarkData": null, "alt": "#初音ミク トラブル２連発 - ねこみん的插画", "titleCaptionTranslation": {"workTitle": null, "workCaption": null}, "createDate": "2017-12-09T22:19:22+09:00", "updateDate": "2017-12-09T22:19:22+09:00", "isUnlisted": false, "isMasked": false, "profileImageUrl": "https://i.pximg.net/user-profile/img/2016/04/04/12/46/47/10760985_e98f4eeb17cb9a352ba66aa4d48a3453_50.png"}, {"id": "66781849", "title": "まとめ", "illustType": 0, "xRestrict": 0, "restrict": 0, "sl": 2, "url": "https://i.pximg.net/c/250x250_80_a2/img-master/img/2018/01/13/17/38/43/66781849_p0_square1200.jpg", "description": "", "tags": ["VOCALOID", "ボカロ", "初音ミク", "鏡音リン"], "userId": "17764467", "userName": "ねこみん", "width": 650, "height": 600, "pageCount": 13, "isBookmarkable": true, "bookmarkData": null, "alt": "#VOCALOID まとめ - ねこみん的插画", "titleCaptionTranslation": {"workTitle": null, "workCaption": null}, "createDate": "2018-01-13T17:38:43+09:00", "updateDate": "2018-01-13T17:38:43+09:00", "isUnlisted": false, "isMasked": false, "profileImageUrl": "https://i.pximg.net/user-profile/img/2016/04/04/12/46/47/10760985_e98f4eeb17cb9a352ba66aa4d48a3453_50.png"}, {"id": "79726513", "title": "魔法未来2019", "illustType": 0, "xRestrict": 0, "restrict": 0, "sl": 2, "url": "https://i.pximg.net/c/250x250_80_a2/img-master/img/2020/02/25/21/34/17/79726513_p0_square1200.jpg", "description": "", "tags": ["初音未来", "miku", "初音ミク", "マジカルミライ2019"], "userId": "7139384", "userName": "sue 一世", "width": 1307, "height": 1118, "pageCount": 1, "isBookmarkable": true, "bookmarkData": null, "alt": "#初音未来 魔法未来2019 - sue 一世的插画", "titleCaptionTranslation": {"workTitle": null, "workCaption": null}, "createDate": "2020-02-25T21:34:17+09:00", "updateDate": "2020-02-25T21:34:17+09:00", "isUnlisted": false, "isMasked": false, "profileImageUrl": "https://i.pximg.net/user-profile/img/2019/05/14/00/20/28/15767404_862c6731b619eec42834f4681d1ca310_50.jpg"}, {"id": "45694825", "title": "Tell Your World", "illustType": 0, "xRestrict": 0, "restrict": 0, "sl": 2, "url": "https://i.pximg.net/c/250x250_80_a2/img-master/img/2014/08/31/03/09/09/45694825_p0_square1200.jpg", "description": "", "tags": ["初音ミク", "VOCALOID", "Tell_Your_World", "初音生誕祭イラスト企画", "ミク誕生祭2014"], "userId": "3649884", "userName": "未琴圭◆10日青海Ｂナ14a", "width": 1390, "height": 1043, "pageCount": 1, "isBookmarkable": true, "bookmarkData": null, "alt": "#初音ミク Tell Your World - 未琴圭◆10日青海Ｂナ14a的插画", "titleCaptionTranslation": {"workTitle": null, "workCaption": null}, "createDate": "2014-08-31T03:09:09+09:00", "updateDate": "2014-08-31T03:09:09+09:00", "isUnlisted": false, "isMasked": false, "profileImageUrl": "https://i.pximg.net/user-profile/img/2020/05/23/17/10/05/18686157_6593716aeadec512083f833015432ad0_50.png"}, {"id": "91066589", "title": "【Latさんスクール】おいで～っ♡", "illustType": 0, "xRestrict": 0, "restrict": 0, "sl": 4, "url": "https://i.pximg.net/c/250x250_80_a2/img-master/img/2021/07/07/01/52/22/91066589_p0_square1200.jpg", "description": "", "tags": ["Latさんスクール", "MikuMikuDance", "MMD", "初音ミク", "Lat式ミク", "ふともも", "足フェチ", "足指", "開脚", "制服素足"], "userId": "16221870", "userName": "海冥", "width": 1500, "height": 1000, "pageCount": 1, "isBookmarkable": true, "bookmarkData": null, "alt": "#Latさんスクール 【Latさんスクール】おいで～っ♡ - 海冥的插画", "titleCaptionTranslation": {"workTitle": null, "workCaption": null}, "createDate": "2021-07-07T01:52:22+09:00", "updateDate": "2021-07-07T01:52:22+09:00", "isUnlisted": false, "isMasked": false, "profileImageUrl": "https://i.pximg.net/user-profile/img/2016/06/27/16/15/45/11121668_a0995c94673a7eee42fa04aa694f85f7_50.png"}, {"id": "72597637", "title": "【1/13 冬インテ 新刊サンプル】 Subconscious", "illustType": 0, "xRestrict": 0, "restrict": 0, "sl": 2, "url": "https://i.pximg.net/c/250x250_80_a2/img-master/img/2019/01/11/00/59/03/72597637_p0_square1200.jpg", "description": "", "tags": ["VOCALOID", "COMICCITY大阪118", "ボーカロイド", "KAITO", "初音ミク", "カイミク", "透明水彩"], "userId": "1401621", "userName": "火葬場", "width": 2000, "height": 1000, "pageCount": 4, "isBookmarkable": true, "bookmarkData": null, "alt": "#VOCALOID 【1/13 冬インテ 新刊サンプル】 Subconscious - 火葬場的插画", "titleCaptionTranslation": {"workTitle": null, "workCaption": null}, "createDate": "2019-01-11T00:59:03+09:00", "updateDate": "2019-01-11T00:59:03+09:00", "isUnlisted": false, "isMasked": false, "profileImageUrl": "https://i.pximg.net/user-profile/img/2020/02/17/00/14/58/17936569_554a9eb7e937386117d4562c233923cf_50.png"}, {"id": "80638845", "title": "はなび", "illustType": 0, "xRestrict": 0, "restrict": 0, "sl": 2, "url": "https://i.pximg.net/c/250x250_80_a2/img-master/img/2020/04/08/02/01/46/80638845_p0_square1200.jpg", "description": "", "tags": ["初音ミク", "初音", "初音ミク2020", "VOCALOID", "少女", "ミク", "miku", "後ろ姿"], "userId": "45442746", "userName": "Rollisy", "width": 1280, "height": 1024, "pageCount": 1, "isBookmarkable": true, "bookmarkData": null, "alt": "#初音ミク はなび - Rollisy的插画", "titleCaptionTranslation": {"workTitle": null, "workCaption": null}, "createDate": "2020-04-08T02:01:46+09:00", "updateDate": "2020-04-08T02:01:46+09:00", "isUnlisted": false, "isMasked": false, "profileImageUrl": "https://i.pximg.net/user-profile/img/2020/03/06/16/38/26/18054525_07d2197f2977e89f01b373d73bca1bd5_50.jpg"}, {"id": "32202069", "title": "リンさ。", "illustType": 0, "xRestrict": 0, "restrict": 0, "sl": 2, "url": "https://i.pximg.net/c/250x250_80_a2/img-master/img/2012/12/19/06/06/35/32202069_p0_square1200.jpg", "description": "", "tags": ["リンミク", "初音ミク"], "userId": "496950", "userName": "かろちん", "width": 619, "height": 546, "pageCount": 1, "isBookmarkable": true, "bookmarkData": null, "alt": "#リンミク リンさ。 - かろちん的插画", "titleCaptionTranslation": {"workTitle": null, "workCaption": null}, "createDate": "2012-12-19T06:06:35+09:00", "updateDate": "2012-12-19T06:06:35+09:00", "isUnlisted": false, "isMasked": false, "profileImageUrl": "https://i.pximg.net/user-profile/img/2011/03/19/18/51/00/2883316_87d1683f388146831ea83ecc46028af7_50.jpg"}, {"id": "79280185", "title": "MIKU", "illustType": 0, "xRestrict": 0, "restrict": 0, "sl": 2, "url": "https://i.pximg.net/c/250x250_80_a2/img-master/img/2020/02/04/17/13/18/79280185_p0_square1200.jpg", "description": "", "tags": ["初音ミク", "MIKU", "美", "VOCALOID"], "userId": "14936855", "userName": "Maloon", "width": 3000, "height": 4200, "pageCount": 1, "isBookmarkable": true, "bookmarkData": null, "alt": "#初音ミク MIKU - Maloon的插画", "titleCaptionTranslation": {"workTitle": null, "workCaption": null}, "createDate": "2020-02-04T17:13:18+09:00", "updateDate": "2020-02-04T17:13:18+09:00", "isUnlisted": false, "isMasked": false, "profileImageUrl": "https://i.pximg.net/user-profile/img/2020/07/11/11/34/21/18969928_d3654bf5059e7c0cccb4042a0c4699d2_50.jpg"}, {"id": "68028513", "title": "無題", "illustType": 0, "xRestrict": 0, "restrict": 0, "sl": 2, "url": "https://i.pximg.net/c/250x250_80_a2/img-master/img/2018/04/01/21/57/39/68028513_p0_square1200.jpg", "description": "", "tags": ["初音ミク", "VOCALOID", "ボカロ"], "userId": "17764467", "userName": "ねこみん", "width": 670, "height": 750, "pageCount": 1, "isBookmarkable": true, "bookmarkData": null, "alt": "#初音ミク 無題 - ねこみん的插画", "titleCaptionTranslation": {"workTitle": null, "workCaption": null}, "createDate": "2018-04-01T21:57:39+09:00", "updateDate": "2018-04-01T21:57:39+09:00", "isUnlisted": false, "isMasked": false, "profileImageUrl": "https://i.pximg.net/user-profile/img/2016/04/04/12/46/47/10760985_e98f4eeb17cb9a352ba66aa4d48a3453_50.png"}, {"id": "62304805", "title": "愛や厭", "illustType": 0, "xRestrict": 0, "restrict": 0, "sl": 2, "url": "https://i.pximg.net/c/250x250_80_a2/img-master/img/2017/04/08/01/07/12/62304805_p0_square1200.jpg", "description": "", "tags": ["水彩", "妄想感傷代償連盟", "DECO*27", "ボーカロイド", "初音ミク", "ボカロ"], "userId": "15795839", "userName": "子鹿", "width": 2827, "height": 3302, "pageCount": 1, "isBookmarkable": true, "bookmarkData": null, "alt": "#水彩 愛や厭 - 子鹿的插画", "titleCaptionTranslation": {"workTitle": null, "workCaption": null}, "createDate": "2017-04-08T01:07:12+09:00", "updateDate": "2017-04-08T01:07:12+09:00", "isUnlisted": false, "isMasked": false, "profileImageUrl": "https://i.pximg.net/user-profile/img/2018/08/18/05/29/41/14651134_48e8c50919109ecc3298ae3203acc24a_50.jpg"}, {"id": "80811593", "title": "ミク", "illustType": 0, "xRestrict": 0, "restrict": 0, "sl": 2, "url": "https://i.pximg.net/c/250x250_80_a2/img-master/img/2020/04/15/19/22/51/80811593_p0_square1200.jpg", "description": "", "tags": ["初音ミク"], "userId": "52629250", "userName": "T", "width": 2039, "height": 1378, "pageCount": 1, "isBookmarkable": true, "bookmarkData": null, "alt": "#初音ミク ミク - T的插画", "titleCaptionTranslation": {"workTitle": null, "workCaption": null}, "createDate": "2020-04-15T19:22:51+09:00", "updateDate": "2020-04-15T19:22:51+09:00", "isUnlisted": false, "isMasked": false, "profileImageUrl": "https://i.pximg.net/user-profile/img/2021/04/10/01/07/55/20507308_582d4a9f55a08b8ae31fca5917e721a6_50.jpg"}, {"id": "49052033", "title": "未来へ", "illustType": 0, "xRestrict": 0, "restrict": 0, "sl": 2, "url": "https://i.pximg.net/c/250x250_80_a2/img-master/img/2015/03/02/18/19/38/49052033_p0_square1200.jpg", "description": "", "tags": ["VOCALOID", "初音ミク", "巡音ルカ", "GUMI", "IA", "鏡音リン", "鏡音レン"], "userId": "8111700", "userName": "千歩＠スランプ", "width": 850, "height": 1122, "pageCount": 1, "isBookmarkable": true, "bookmarkData": null, "alt": "#VOCALOID 未来へ - 千歩＠スランプ的插画", "titleCaptionTranslation": {"workTitle": null, "workCaption": null}, "createDate": "2015-03-02T18:19:38+09:00", "updateDate": "2015-03-02T18:19:38+09:00", "isUnlisted": false, "isMasked": false, "profileImageUrl": "https://i.pximg.net/user-profile/img/2013/12/12/03/14/53/7163343_9cc40b2985950cfe7d1959f0254b8663_50.jpg"}, {"id": "67363813", "title": "砂の惑星", "illustType": 0, "xRestrict": 0, "restrict": 0, "sl": 2, "url": "https://i.pximg.net/c/250x250_80_a2/img-master/img/2018/02/19/23/55/28/67363813_p0_square1200.jpg", "description": "", "tags": ["VOCALOID", "マジ砂", "初音ミク", "砂の惑星"], "userId": "16752089", "userName": "ねむねこ", "width": 768, "height": 1024, "pageCount": 1, "isBookmarkable": true, "bookmarkData": null, "alt": "#VOCALOID 砂の惑星 - ねむねこ的插画", "titleCaptionTranslation": {"workTitle": null, "workCaption": null}, "createDate": "2018-02-19T23:55:28+09:00", "updateDate": "2018-02-19T23:55:28+09:00", "isUnlisted": false, "isMasked": false, "profileImageUrl": "https://i.pximg.net/user-profile/img/2020/11/07/11/19/14/19629084_aa637da126423e02667774c1fe672c3e_50.jpg"}, {"id": "17948737", "title": "スイーツハウスへようこそ！", "illustType": 0, "xRestrict": 0, "restrict": 0, "sl": 2, "url": "https://i.pximg.net/c/250x250_80_a2/img-master/img/2011/04/06/00/05/32/17948737_p0_square1200.jpg", "description": "", "tags": ["VOCALOID", "リンミク", "初音ミク", "鏡音リン", "はいてない"], "userId": "151361", "userName": "せきはら＊BOOTH通販中", "width": 700, "height": 700, "pageCount": 1, "isBookmarkable": true, "bookmarkData": null, "alt": "#VOCALOID スイーツハウスへようこそ！ - せきはら＊BOOTH通販中的插画", "titleCaptionTranslation": {"workTitle": null, "workCaption": null}, "createDate": "2011-04-06T00:05:32+09:00", "updateDate": "2011-04-06T00:05:32+09:00", "isUnlisted": false, "isMasked": false, "profileImageUrl": "https://i.pximg.net/user-profile/img/2020/10/05/19/24/34/19465233_71fe7590443e8e4f3509c88ff8f6e08b_50.png"}, {"id": "86743965", "title": "snowmiku2021", "illustType": 0, "xRestrict": 0, "restrict": 0, "sl": 2, "url": "https://i.pximg.net/c/250x250_80_a2/img-master/img/2021/01/02/00/47/28/86743965_p0_square1200.jpg", "description": "", "tags": ["VOCALOID", "snowmiku2021", "雪ミク2021", "初音ミク"], "userId": "30213719", "userName": "もや", "width": 1006, "height": 1346, "pageCount": 1, "isBookmarkable": true, "bookmarkData": null, "alt": "#VOCALOID snowmiku2021 - もや的插画", "titleCaptionTranslation": {"workTitle": null, "workCaption": null}, "createDate": "2021-01-02T00:47:28+09:00", "updateDate": "2021-01-02T00:47:28+09:00", "isUnlisted": false, "isMasked": false, "profileImageUrl": "https://s.pximg.net/common/images/no_profile_s.png"}, {"id": "44231953", "title": "MIKU", "illustType": 0, "xRestrict": 0, "restrict": 0, "sl": 2, "url": "https://i.pximg.net/c/250x250_80_a2/img-master/img/2014/06/22/00/28/35/44231953_p0_square1200.jpg", "description": "", "tags": ["花嫁", "vocaloid", "ウェディングドレス", "miku", "初音未来", "初音ミク"], "userId": "5394742", "userName": "Rev", "width": 885, "height": 1289, "pageCount": 1, "isBookmarkable": true, "bookmarkData": null, "alt": "#花嫁 MIKU - Rev的插画", "titleCaptionTranslation": {"workTitle": null, "workCaption": null}, "createDate": "2014-06-22T00:28:35+09:00", "updateDate": "2014-06-22T00:28:35+09:00", "isUnlisted": false, "isMasked": false, "profileImageUrl": "https://i.pximg.net/user-profile/img/2019/02/03/07/28/10/15342794_3531a0bfa84957217d35da6b869a4448_50.jpg"}, {"id": "71309081", "title": "初音ミク (バレンタイン)", "illustType": 0, "xRestrict": 0, "restrict": 0, "sl": 2, "url": "https://i.pximg.net/c/250x250_80_a2/img-master/img/2018/10/23/02/39/59/71309081_p0_square1200.jpg", "description": "", "tags": ["初音ミク", "バレンタイン", "kawaii", "Vocaloid", "Tsundere", "チョコレート", "ツインテール"], "userId": "27519698", "userName": "Akane Rose", "width": 1843, "height": 2059, "pageCount": 1, "isBookmarkable": true, "bookmarkData": null, "alt": "#初音ミク 初音ミク (バレンタイン) - Akane Rose的插画", "titleCaptionTranslation": {"workTitle": null, "workCaption": null}, "createDate": "2018-10-23T02:39:59+09:00", "updateDate": "2018-10-23T02:39:59+09:00", "isUnlisted": false, "isMasked": false, "profileImageUrl": "https://i.pximg.net/user-profile/img/2020/01/15/13/18/59/16856554_472d311e0cf00f354250258b3ff56d23_50.png"}, {"id": "80002413", "title": "みくのひ！", "illustType": 0, "xRestrict": 0, "restrict": 0, "sl": 2, "url": "https://i.pximg.net/c/250x250_80_a2/img-master/img/2020/03/09/16/45/39/80002413_p0_square1200.jpg", "description": "", "tags": ["ミクの日", "初音ミク", "ミクの日2020"], "userId": "21795938", "userName": "左ノ丸", "width": 2894, "height": 4093, "pageCount": 1, "isBookmarkable": true, "bookmarkData": null, "alt": "#ミクの日 みくのひ！ - 左ノ丸的插画", "titleCaptionTranslation": {"workTitle": null, "workCaption": null}, "createDate": "2020-03-09T16:45:39+09:00", "updateDate": "2020-03-09T16:45:39+09:00", "isUnlisted": false, "isMasked": false, "profileImageUrl": "https://i.pximg.net/user-profile/img/2020/03/01/01/26/48/18017950_c5ed4b7a6017f567288e1d24f84c9924_50.jpg"}, {"id": "64735345", "title": "Happy Birthday!", "illustType": 0, "xRestrict": 0, "restrict": 0, "sl": 2, "url": "https://i.pximg.net/c/250x250_80_a2/img-master/img/2017/09/01/20/21/43/64735345_p0_square1200.jpg", "description": "", "tags": ["初音ミク生誕祭2017", "miku", "初音ミク", "初音ミク10thイラコン"], "userId": "20744352", "userName": "鹿しいか", "width": 516, "height": 729, "pageCount": 2, "isBookmarkable": true, "bookmarkData": null, "alt": "#初音ミク生誕祭2017 Happy Birthday! - 鹿しいか的插画", "titleCaptionTranslation": {"workTitle": null, "workCaption": null}, "createDate": "2017-09-01T20:21:43+09:00", "updateDate": "2017-09-01T20:21:43+09:00", "isUnlisted": false, "isMasked": false, "profileImageUrl": "https://i.pximg.net/user-profile/img/2021/07/30/03/59/07/21125276_1c42fe1775a54286363916eb5ea259a4_50.png"}, {"id": "29770269", "title": "今すぐ　抱きしめて", "illustType": 0, "xRestrict": 0, "restrict": 0, "sl": 2, "url": "https://i.pximg.net/c/250x250_80_a2/img-master/img/2012/08/31/00/00/08/29770269_p0_square1200.jpg", "description": "", "tags": ["VOCALOID", "初音ミク", "8月の花嫁", "ミク誕生祭2012"], "userId": "1608289", "userName": "前", "width": 720, "height": 720, "pageCount": 1, "isBookmarkable": true, "bookmarkData": null, "alt": "#VOCALOID 今すぐ　抱きしめて - 前的插画", "titleCaptionTranslation": {"workTitle": null, "workCaption": null}, "createDate": "2012-08-31T00:00:08+09:00", "updateDate": "2012-08-31T00:00:08+09:00", "isUnlisted": false, "isMasked": false, "profileImageUrl": "https://i.pximg.net/user-profile/img/2013/09/18/19/48/28/6831788_264e7f368015dbbbfcbefb6c4667d854_50.png"}, {"id": "84995829", "title": "初音ミク", "illustType": 0, "xRestrict": 0, "restrict": 0, "sl": 2, "url": "https://i.pximg.net/c/250x250_80_a2/img-master/img/2020/10/13/22/34/23/84995829_p0_square1200.jpg", "description": "", "tags": ["初音ミク", "プロセカ", "VOCALOID", "プロジェクトセカイ", "ニーゴミク"], "userId": "18180245", "userName": "雪屋", "width": 7056, "height": 6889, "pageCount": 1, "isBookmarkable": true, "bookmarkData": null, "alt": "#初音ミク 初音ミク - 雪屋的插画", "titleCaptionTranslation": {"workTitle": null, "workCaption": null}, "createDate": "2020-10-13T22:34:23+09:00", "updateDate": "2020-10-13T22:34:23+09:00", "isUnlisted": false, "isMasked": false, "profileImageUrl": "https://i.pximg.net/user-profile/img/2021/04/04/22/55/52/20478231_2755a0c792a398ea92f5b87a65c69f42_50.jpg"}, {"id": "5370853", "title": "家の裏でＫＡＩＴＯがしんでる2", "illustType": 0, "xRestrict": 0, "restrict": 0, "sl": 2, "url": "https://i.pximg.net/c/250x250_80_a2/img-master/img/2009/07/29/01/36/56/5370853_p0_square1200.jpg", "description": "", "tags": ["ネギトロ", "ルッカバスター", "初音ミク", "巡音ルカ", "百合", "magnetごっこ", "magnetごっこ見たい", "vocaloid", "みっ"], "userId": "47896", "userName": "朧月カケル", "width": 560, "height": 1552, "pageCount": 1, "isBookmarkable": true, "bookmarkData": null, "alt": "#ネギトロ 家の裏でＫＡＩＴＯがしんでる2 - 朧月カケル的插画", "titleCaptionTranslation": {"workTitle": null, "workCaption": null}, "createDate": "2009-07-29T01:36:56+09:00", "updateDate": "2009-07-29T01:36:56+09:00", "isUnlisted": false, "isMasked": false, "profileImageUrl": "https://i.pximg.net/user-profile/img/2009/06/03/21/23/00/811966_b0b31d58006e497a20eb113c96a1d344_50.jpg"}, {"id": "71859757", "title": "ミクちゃん", "illustType": 0, "xRestrict": 0, "restrict": 0, "sl": 2, "url": "https://i.pximg.net/c/250x250_80_a2/img-master/img/2018/11/27/21/46/10/71859757_p0_square1200.jpg", "description": "", "tags": ["ミク", "初音ミク", "ありがとう", "イラスト"], "userId": "30044684", "userName": "橘 ワタル", "width": 2224, "height": 1668, "pageCount": 1, "isBookmarkable": true, "bookmarkData": null, "alt": "#ミク ミクちゃん - 橘 ワタル的插画", "titleCaptionTranslation": {"workTitle": null, "workCaption": null}, "createDate": "2018-11-27T21:46:10+09:00", "updateDate": "2018-11-27T21:46:10+09:00", "isUnlisted": false, "isMasked": false, "profileImageUrl": "https://i.pximg.net/user-profile/img/2018/12/02/00/28/36/15079930_66d141eba487b26b7096238288704bf2_50.jpg"}, {"id": "63997793", "title": "砂の惑星", "illustType": 0, "xRestrict": 0, "restrict": 0, "sl": 2, "url": "https://i.pximg.net/c/250x250_80_a2/img-master/img/2017/07/22/23/05/44/63997793_p0_square1200.jpg", "description": "", "tags": ["VOCALOID", "初音ミク", "砂の惑星", "ハチ"], "userId": "545875", "userName": "anmo", "width": 1600, "height": 1600, "pageCount": 1, "isBookmarkable": true, "bookmarkData": null, "alt": "#VOCALOID 砂の惑星 - anmo的插画", "titleCaptionTranslation": {"workTitle": null, "workCaption": null}, "createDate": "2017-07-22T23:05:44+09:00", "updateDate": "2017-07-22T23:05:44+09:00", "isUnlisted": false, "isMasked": false, "profileImageUrl": "https://i.pximg.net/user-profile/img/2013/07/31/20/24/24/6595222_6cced7379c8c6ca4662ed83b021ad00e_50.png"}, {"id": "59645457", "title": "同人誌・お試し読み", "illustType": 1, "xRestrict": 0, "restrict": 0, "sl": 2, "url": "https://i.pximg.net/c/250x250_80_a2/img-master/img/2016/10/26/17/06/07/59645457_p0_square1200.jpg", "description": "", "tags": ["漫画", "初音ミク", "アナログ", "VOCALOID"], "userId": "8392323", "userName": "しろ紅茶", "width": 2196, "height": 3067, "pageCount": 5, "isBookmarkable": true, "bookmarkData": null, "alt": "#初音ミク 同人誌・お試し読み - しろ紅茶的漫画", "titleCaptionTranslation": {"workTitle": null, "workCaption": null}, "createDate": "2016-10-26T17:06:07+09:00", "updateDate": "2016-10-26T17:06:07+09:00", "isUnlisted": false, "isMasked": false, "profileImageUrl": "https://i.pximg.net/user-profile/img/2021/06/09/17/52/33/20845896_f0cdc46571e1037c353fb99fb57c0454_50.jpg"}, {"id": "69258945", "title": "Racingmiku", "illustType": 0, "xRestrict": 0, "restrict": 0, "sl": 2, "url": "https://i.pximg.net/c/250x250_80_a2/img-master/img/2018/06/16/20/01/41/69258945_p0_square1200.jpg", "description": "", "tags": ["Miku", "RacingMiku2014", "GSR", "VOCALOID", "初音ミク", "レーシングミク", "レーシングミク2014"], "userId": "24970708", "userName": "東方憶白er", "width": 2311, "height": 3264, "pageCount": 1, "isBookmarkable": true, "bookmarkData": null, "alt": "#Miku Racingmiku - 東方憶白er的插画", "titleCaptionTranslation": {"workTitle": null, "workCaption": null}, "createDate": "2018-06-16T20:01:41+09:00", "updateDate": "2018-06-16T20:01:41+09:00", "isUnlisted": false, "isMasked": false, "profileImageUrl": "https://i.pximg.net/user-profile/img/2018/01/13/23/10/36/13689547_5bc0bf8474bd3d964ad5c724316bc9d5_50.jpg"}, {"id": "84611817", "title": "雪ミクtaker ver.2020（Helltaker)", "illustType": 2, "xRestrict": 0, "restrict": 0, "sl": 2, "url": "https://i.pximg.net/c/250x250_80_a2/img-master/img/2020/09/26/01/47/59/84611817_square1200.jpg", "description": "", "tags": ["动图", "Helltaker", "初音ミク", "Live2d製"], "userId": "50694238", "userName": "Neko_ kk", "width": 1024, "height": 1024, "pageCount": 1, "isBookmarkable": true, "bookmarkData": null, "alt": "#动图 雪ミクtaker ver.2020（Helltaker) - Neko_ kk的动图", "titleCaptionTranslation": {"workTitle": null, "workCaption": null}, "createDate": "2020-09-26T01:47:59+09:00", "updateDate": "2020-09-26T01:47:59+09:00", "isUnlisted": false, "isMasked": false, "profileImageUrl": "https://i.pximg.net/user-profile/img/2020/03/07/00/42/54/18057468_2123294e145f59e5dec1213ae9e9e048_50.jpg"}, {"id": "32060649", "title": "おにんにんがない話001～010（多分単発）", "illustType": 1, "xRestrict": 0, "restrict": 0, "sl": 6, "url": "https://i.pximg.net/c/250x250_80_a2/img-master/img/2012/12/12/05/04/16/32060649_p0_square1200.jpg", "description": "", "tags": ["漫画", "鏡音リン", "鏡音レン", "ぼかまん", "VOCALOID", "初音ミク", "TSF", "レンリン", "リンより女の子みたいなレン"], "userId": "166313", "userName": "namakobcg（乱数P）", "width": 320, "height": 1020, "pageCount": 10, "isBookmarkable": true, "bookmarkData": null, "alt": "#鏡音リン おにんにんがない話001～010（多分単発） - namakobcg（乱数P）的漫画", "titleCaptionTranslation": {"workTitle": null, "workCaption": null}, "createDate": "2012-12-12T05:04:16+09:00", "updateDate": "2012-12-12T05:04:16+09:00", "isUnlisted": false, "isMasked": false, "profileImageUrl": "https://i.pximg.net/user-profile/img/2016/05/22/15/01/04/10964825_06e94ce41dd2ec372affb93b939e2dd7_50.png"}, {"id": "43407557", "title": "MMDで壁紙を！こーひーぶれいく", "illustType": 0, "xRestrict": 0, "restrict": 0, "sl": 2, "url": "https://i.pximg.net/c/250x250_80_a2/img-master/img/2014/05/10/01/49/16/43407557_p0_square1200.jpg", "description": "", "tags": ["MMD", "MikuMikuDance", "初音ミク", "VOCALOID", "壁紙", "全画面推奨", "Tda式Appendミク"], "userId": "6391116", "userName": "アヤホ", "width": 2560, "height": 1440, "pageCount": 1, "isBookmarkable": true, "bookmarkData": null, "alt": "#MMD MMDで壁紙を！こーひーぶれいく - アヤホ的插画", "titleCaptionTranslation": {"workTitle": null, "workCaption": null}, "createDate": "2014-05-10T01:49:16+09:00", "updateDate": "2014-05-10T01:49:16+09:00", "isUnlisted": false, "isMasked": false, "profileImageUrl": "https://i.pximg.net/user-profile/img/2016/05/04/18/18/50/10887287_d36128517dbecfac8b513bdfe6fe1137_50.png"}, {"id": "87627809", "title": "ミクさん　(リクエスト品)", "illustType": 0, "xRestrict": 0, "restrict": 0, "sl": 4, "url": "https://i.pximg.net/c/250x250_80_a2/img-master/img/2021/02/08/21/36/40/87627809_p0_square1200.jpg", "description": "", "tags": ["初音ミク", "VOCALOID", "MMD"], "userId": "2377459", "userName": "マージナルマン", "width": 1920, "height": 1080, "pageCount": 1, "isBookmarkable": true, "bookmarkData": null, "alt": "#初音ミク ミクさん　(リクエスト品) - マージナルマン的插画", "titleCaptionTranslation": {"workTitle": null, "workCaption": null}, "createDate": "2021-02-08T21:36:40+09:00", "updateDate": "2021-02-08T21:36:40+09:00", "isUnlisted": false, "isMasked": false, "profileImageUrl": "https://i.pximg.net/user-profile/img/2017/05/03/09/05/07/12503669_2f05dde97293af34785c1151e7511e7a_50.jpg"}, {"id": "32609305", "title": "商店街戦争", "illustType": 0, "xRestrict": 0, "restrict": 0, "sl": 2, "url": "https://i.pximg.net/c/250x250_80_a2/img-master/img/2013/01/03/20/10/48/32609305_p0_square1200.jpg", "description": "", "tags": ["初音ミク", "風景", "商店街"], "userId": "4668928", "userName": "しそのは", "width": 1024, "height": 768, "pageCount": 1, "isBookmarkable": true, "bookmarkData": null, "alt": "#初音ミク 商店街戦争 - しそのは的插画", "titleCaptionTranslation": {"workTitle": null, "workCaption": null}, "createDate": "2013-01-03T20:10:48+09:00", "updateDate": "2013-01-03T20:10:48+09:00", "isUnlisted": false, "isMasked": false, "profileImageUrl": "https://i.pximg.net/user-profile/img/2016/01/07/21/13/34/10350234_88dee96aadc6f205081dbcf883aad7cb_50.jpg"}, {"id": "44266825", "title": "コクピット", "illustType": 0, "xRestrict": 0, "restrict": 0, "sl": 2, "url": "https://i.pximg.net/c/250x250_80_a2/img-master/img/2014/06/23/18/33/46/44266825_p0_square1200.jpg", "description": "", "tags": ["MMD", "MikuMikuDance", "初音ミク", "フォトジェミック", "NSX", "レーシングミク"], "userId": "2700482", "userName": "♪♪夕凪", "width": 2327, "height": 1417, "pageCount": 1, "isBookmarkable": true, "bookmarkData": null, "alt": "#MMD コクピット - ♪♪夕凪的插画", "titleCaptionTranslation": {"workTitle": null, "workCaption": null}, "createDate": "2014-06-23T18:33:46+09:00", "updateDate": "2014-06-23T18:33:46+09:00", "isUnlisted": false, "isMasked": false, "profileImageUrl": "https://i.pximg.net/user-profile/img/2020/06/26/06/23/03/18887234_5c9fa58243a1c1781b9a2ae1de3a55e0_50.jpg"}, {"id": "76818217", "title": "みくさん", "illustType": 0, "xRestrict": 0, "restrict": 0, "sl": 2, "url": "https://i.pximg.net/c/250x250_80_a2/img-master/img/2019/09/16/21/09/09/76818217_p0_square1200.jpg", "description": "", "tags": ["Vocaloid", "初音ミク"], "userId": "1969060", "userName": "はつねネガメ", "width": 2507, "height": 3541, "pageCount": 1, "isBookmarkable": true, "bookmarkData": null, "alt": "#Vocaloid みくさん - はつねネガメ的插画", "titleCaptionTranslation": {"workTitle": null, "workCaption": null}, "createDate": "2019-09-16T21:09:09+09:00", "updateDate": "2019-09-16T21:09:09+09:00", "isUnlisted": false, "isMasked": false, "profileImageUrl": "https://i.pximg.net/user-profile/img/2013/07/11/18/45/34/6494272_bd8c9aaf4013ebeaf1f1fc15b49cccbb_50.jpg"}, {"id": "74557069", "title": "4/5/2019", "illustType": 0, "xRestrict": 0, "restrict": 0, "sl": 2, "url": "https://i.pximg.net/c/250x250_80_a2/img-master/img/2019/05/04/20/28/25/74557069_p0_square1200.jpg", "description": "", "tags": ["VOCALOID", "クオミク", "初音ミク", "初音ミクオ", "ボーカロイド", "GUMI", "GUMIYA", "水着", "ぐみっぱい", "ミヤグミ"], "userId": "10626282", "userName": "Chi", "width": 900, "height": 800, "pageCount": 2, "isBookmarkable": true, "bookmarkData": null, "alt": "#VOCALOID 4/5/2019 - Chi的插画", "titleCaptionTranslation": {"workTitle": null, "workCaption": null}, "createDate": "2019-05-04T20:28:25+09:00", "updateDate": "2019-05-04T20:28:25+09:00", "isUnlisted": false, "isMasked": false, "profileImageUrl": "https://i.pximg.net/user-profile/img/2020/05/16/17/53/23/18630189_389d50ec70c196a41359530fa29b7831_50.png"}, {"id": "11985813", "title": "ミク、夏休みの研究", "illustType": 0, "xRestrict": 0, "restrict": 0, "sl": 6, "url": "https://i.pximg.net/c/250x250_80_a2/img-master/img/2010/07/19/19/12/20/11985813_p0_square1200.jpg", "description": "", "tags": ["初音ミク", "手を離せば止められる", "電マ", "アーフ", "電アン", "×とめられない○やめられない", "電マロイド", "R-15", "サイハイソックス"], "userId": "26746", "userName": "くろくぅ", "width": 999, "height": 894, "pageCount": 1, "isBookmarkable": true, "bookmarkData": null, "alt": "#初音ミク ミク、夏休みの研究 - くろくぅ的插画", "titleCaptionTranslation": {"workTitle": null, "workCaption": null}, "createDate": "2010-07-19T19:12:20+09:00", "updateDate": "2010-07-19T19:12:20+09:00", "isUnlisted": false, "isMasked": false, "profileImageUrl": "https://i.pximg.net/user-profile/img/2008/10/14/07/03/05/327464_4f645b01b0e38300cf646ff6f205617a_50.jpg"}, {"id": "30604765", "title": "みくネコ", "illustType": 0, "xRestrict": 0, "restrict": 0, "sl": 2, "url": "https://i.pximg.net/c/250x250_80_a2/img-master/img/2012/10/06/01/06/06/30604765_p0_square1200.jpg", "description": "", "tags": ["初音ミク", "水着", "猫耳"], "userId": "2515081", "userName": "ななみやりん@お仕事募集中", "width": 500, "height": 687, "pageCount": 1, "isBookmarkable": true, "bookmarkData": null, "alt": "#初音ミク みくネコ - ななみやりん@お仕事募集中的插画", "titleCaptionTranslation": {"workTitle": null, "workCaption": null}, "createDate": "2012-10-06T01:06:06+09:00", "updateDate": "2012-10-06T01:06:06+09:00", "isUnlisted": false, "isMasked": false, "profileImageUrl": "https://i.pximg.net/user-profile/img/2014/01/09/18/20/01/7284541_6c1df1f45db471a7abde42a2a51b0ca8_50.jpg"}]